prepembd/__init__.py
prepembd/bin/__init__.py
prepembd/bin/tokenize.py
prepembd/lib/__init__.py
prepembd/lib/helper.py
prepembd/lib/path.py
prepembd-0.3.0.dist-info/METADATA
prepembd-0.3.0.dist-info/WHEEL
prepembd-0.3.0.dist-info/entry_points.txt
prepembd-0.3.0.dist-info/top_level.txt
prepembd-0.3.0.dist-info/RECORD
