Metadata-Version: 2.4
Name: prepembd
Version: 0.3.0
Summary: prepembd
Author-email: sysid <sysid@gmx.de>
License: MIT
Requires-Python: >=3.12
Requires-Dist: langchain>=0.3.02
Requires-Dist: tiktoken>=0.6.0
Requires-Dist: unstructured>=0.11.8
Requires-Dist: nltk>=3.8.1
Requires-Dist: typer>=0.9.0
Requires-Dist: markdown>=3.6
